getwowdata/__init__.py
getwowdata/exceptions.py
getwowdata/getdata.py
getwowdata/helpers.py
getwowdata/urls.py
get_wow_data-0.1.8.3.dist-info/METADATA
get_wow_data-0.1.8.3.dist-info/WHEEL
get_wow_data-0.1.8.3.dist-info/top_level.txt
get_wow_data-0.1.8.3.dist-info/RECORD
