Metadata-Version: 2.1
Name: get-wow-data
Version: 0.1.8.3
Summary: Provides methods that make requests to specific World of Warcraft API's
Home-page: https://github.com/JackBorah/get-wow-data
Author: Jack Borah
Author-email: borahjack@gmail.com
License: MIT
Keywords: World of Warcraft
Platform: any
Classifier: Development Status :: 3 - Alpha
Classifier: Intended Audience :: Developers
Classifier: Programming Language :: Python :: 3
Classifier: Operating System :: OS Independent
Classifier: License :: OSI Approved :: MIT License
Classifier: Topic :: Software Development :: Libraries :: Python Modules
Requires-Dist: requests
